texonomy/__init__.py
texonomy/_version.py
texonomy/texonomy.py
texonomy/templates/__init__.py
texonomy/templates/template.tex
texonomy/tests/test_entity.py
texonomy/tests/test_erd.py
texonomy/tests/test_line.py
texonomy/tests/integration_tests/Makefile
texonomy/tests/integration_tests/entity.py
texonomy/tests/integration_tests/kitchensink.py
texonomy/tests/integration_tests/relattr.py
texonomy/tests/integration_tests/run_tests.sh
texonomy/tests/integration_tests/specialization.py
texonomy/tests/integration_tests/weakentity.py
texonomy-0.1.1.dist-info/LICENSE
texonomy-0.1.1.dist-info/METADATA
texonomy-0.1.1.dist-info/WHEEL
texonomy-0.1.1.dist-info/top_level.txt
texonomy-0.1.1.dist-info/RECORD
