Metadata-Version: 2.1
Name: texonomy
Version: 0.1.1
Summary: A tool that generates entity-relationship diagrams in LaTeX.
Author-email: Ivy Basseches <imb2139@columbia.edu>
License: Apache License
Project-URL: repository, https://github.com/basseches/texonomy
Requires-Python: >=3.8
License-File: LICENSE
Provides-Extra: develop
Requires-Dist: black (>=22) ; extra == 'develop'
Requires-Dist: check-manifest ; extra == 'develop'
Requires-Dist: flake8 (>=3.7.8) ; extra == 'develop'
Requires-Dist: flake8-black (>=0.2.1) ; extra == 'develop'
Requires-Dist: flake8-pyproject ; extra == 'develop'
Requires-Dist: mypy ; extra == 'develop'
Requires-Dist: pytest (>=4.3.0) ; extra == 'develop'
Requires-Dist: pytest-cov (>=2.6.1) ; extra == 'develop'
Requires-Dist: twine ; extra == 'develop'
Requires-Dist: wheel ; extra == 'develop'
